{"cameraMode":{"drawMode":0,"name":"Shaded","section":"Shading Mode"},"sceneLighting":false,"audioPlay":false,"sceneViewState":{"m_AlwaysRefresh":false,"showFog":true,"showSkybox":false,"showFlares":true,"showImageEffects":true,"showParticleSystems":true,"showVisualEffectGraphs":true,"m_FxEnabled":true},"in2DMode":false,"pivot":{"x":-0.9155006408691406,"y":-5.15377140045166,"z":7.802768707275391},"rotation":{"x":-0.28365230560302737,"y":0.5923222303390503,"z":-0.23438964784145356,"w":-0.7167984843254089},"size":0.8660253882408142,"orthographic":false}